README.md
setup.cfg
setup.py
TOPSIS_Siddharth_101816019/topsis.py
TOPSIS_Siddharth_101816019.egg-info/PKG-INFO
TOPSIS_Siddharth_101816019.egg-info/SOURCES.txt
TOPSIS_Siddharth_101816019.egg-info/dependency_links.txt
TOPSIS_Siddharth_101816019.egg-info/entry_points.txt
TOPSIS_Siddharth_101816019.egg-info/requires.txt
TOPSIS_Siddharth_101816019.egg-info/top_level.txt